ZuizhongyaodeshiZhiyouYijian/README.md
ZuizhongyaodeshiZhiyouYijian/__init__.py
ZuizhongyaodeshiZhiyouYijian/__main__.py
ZuizhongyaodeshiZhiyouYijian/file.epub
ZuizhongyaodeshiZhiyouYijian/index.html
ZuizhongyaodeshiZhiyouYijian/css/__init__.py
ZuizhongyaodeshiZhiyouYijian/css/annotations.css
ZuizhongyaodeshiZhiyouYijian/css/main.css
ZuizhongyaodeshiZhiyouYijian/css/normalize.css
ZuizhongyaodeshiZhiyouYijian/css/popup.css
ZuizhongyaodeshiZhiyouYijian/font/__init__.py
ZuizhongyaodeshiZhiyouYijian/font/fontello.eot
ZuizhongyaodeshiZhiyouYijian/font/fontello.svg
ZuizhongyaodeshiZhiyouYijian/font/fontello.ttf
ZuizhongyaodeshiZhiyouYijian/font/fontello.woff
ZuizhongyaodeshiZhiyouYijian/img/__init__.py
ZuizhongyaodeshiZhiyouYijian/img/annotator-glyph-sprite.png
ZuizhongyaodeshiZhiyouYijian/img/annotator-icon-sprite.png
ZuizhongyaodeshiZhiyouYijian/img/apple-touch-icon.png
ZuizhongyaodeshiZhiyouYijian/img/cancelfullscreen.png
ZuizhongyaodeshiZhiyouYijian/img/close.png
ZuizhongyaodeshiZhiyouYijian/img/fullscreen.png
ZuizhongyaodeshiZhiyouYijian/img/loader.gif
ZuizhongyaodeshiZhiyouYijian/img/menu-icon.png
ZuizhongyaodeshiZhiyouYijian/img/save.png
ZuizhongyaodeshiZhiyouYijian/img/saved.png
ZuizhongyaodeshiZhiyouYijian/img/settings-s.png
ZuizhongyaodeshiZhiyouYijian/img/settings.png
ZuizhongyaodeshiZhiyouYijian/img/star.png
ZuizhongyaodeshiZhiyouYijian/js/__init__.py
ZuizhongyaodeshiZhiyouYijian/js/epub.js
ZuizhongyaodeshiZhiyouYijian/js/epub.min.js
ZuizhongyaodeshiZhiyouYijian/js/epub.min.map
ZuizhongyaodeshiZhiyouYijian/js/hooks.min.js
ZuizhongyaodeshiZhiyouYijian/js/hooks.min.map
ZuizhongyaodeshiZhiyouYijian/js/reader.js
ZuizhongyaodeshiZhiyouYijian/js/reader.js.map
ZuizhongyaodeshiZhiyouYijian/js/reader.min.js
ZuizhongyaodeshiZhiyouYijian/js/reader.min.map
ZuizhongyaodeshiZhiyouYijian/js/hooks/__init__.py
ZuizhongyaodeshiZhiyouYijian/js/hooks/extensions/__init__.py
ZuizhongyaodeshiZhiyouYijian/js/hooks/extensions/highlight.js
zuizhongyaodeshi_zhiyou_yijian-2022.10.15.0.dist-info/METADATA
zuizhongyaodeshi_zhiyou_yijian-2022.10.15.0.dist-info/WHEEL
zuizhongyaodeshi_zhiyou_yijian-2022.10.15.0.dist-info/entry_points.txt
zuizhongyaodeshi_zhiyou_yijian-2022.10.15.0.dist-info/top_level.txt
zuizhongyaodeshi_zhiyou_yijian-2022.10.15.0.dist-info/RECORD
